pyplots/__init__.py
pyplots/_base_plot.py
pyplots/_color.py
pyplots/_legend.py
pyplots/_show.py
pyplots/cartesian/__init__.py
pyplots/cartesian/_grid.py
pyplots/cartesian/_line.py
pyplots/cartesian/_plot.py
pyplots/cartesian/_plot_object.py
pyplots/cartesian/_scatter.py
pyplots/cartesian/_sub_plots.py
pyplots/text/__init__.py
pyplots/text/_alignment.py
pyplots/text/_font.py
pyplots/text/_format.py
pyplots-0.2.8.dist-info/LICENSE
pyplots-0.2.8.dist-info/METADATA
pyplots-0.2.8.dist-info/WHEEL
pyplots-0.2.8.dist-info/top_level.txt
pyplots-0.2.8.dist-info/RECORD
