Metadata-Version: 2.1
Name: pyplots
Version: 0.2.8
Summary: Wraps matplotlib for easier plotting.
Home-page: https://github.com/jakkes/pyplots
Author: Jakob Stigenberg
License: UNKNOWN
Platform: UNKNOWN
Classifier: Programming Language :: Python :: 3
Classifier: License :: OSI Approved :: MIT License
Classifier: Operating System :: OS Independent
Requires-Python: >=3.7
License-File: LICENSE
Requires-Dist: matplotlib (~=3.4.3)
